{
  "GroupGUID": null,
  "GroupName": "Room_B3_MPF",
  "Category": "Normal",
  "ConfigPrefabPath": null,
  "LevelGraph": "Config/Level/GroupGraph/F20331001/Group_F20331001_G13.json",
  "AreaAnchorName": "LevelArea_P20331_F20331001_G13",
  "SaveType": "Permanent",
  "SaveDimensionFilter": null,
  "LoadCondition": null,
  "UnloadCondition": null,
  "ForceUnloadCondition": null,
  "SavedValueCondition": {
    "Conditions": [],
    "Operation": "And"
  },
  "SystemUnlockCondition": null,
  "AtmosphereCondition": null,
  "UseCustomSaveData": false,
  "IsPendedLoad": false,
  "IsPendedUnload": false,
  "LoadSide": "Server",
  "LoadOnInitial": true,
  "OwnerMainMissionID": 0,
  "AirlineInitPrefabPaths": null,
  "RandomInit": null,
  "GroupStateList": null,
  "GroupRefreshID": 0,
  "ValueSource": {
    "Values": null,
    "SharedValues": null
  },
  "ConflictIDList": [],
  "IsHoyoGroup": true,
  "HoYoGroupType": "Standard",
  "StreamingTemplateType": "None",
  "ConflictWhiteList": [],
  "EnableGroupAI": false,
  "AnchorList": [
    {
      "RotX": 0.0,
      "RotZ": 0.0,
      "Usage": "Unspecified",
      "LookAtCameraTemplate": null,
      "CustomParameter": null,
      "Name": "pos1",
      "RotY": 0.0,
      "ID": 1,
      "PosX": 402.9,
      "PosY": -15.6,
      "PosZ": 820.8,
      "IsDelete": false
    },
    {
      "RotX": 0.0,
      "RotZ": 0.0,
      "Usage": "Unspecified",
      "LookAtCameraTemplate": null,
      "CustomParameter": null,
      "Name": "pos2",
      "RotY": 0.0,
      "ID": 2,
      "PosX": 402.9,
      "PosY": -15.6,
      "PosZ": 842.6,
      "IsDelete": false
    },
    {
      "RotX": 39.28561,
      "RotZ": -1E-06,
      "Usage": "Camera",
      "LookAtCameraTemplate": null,
      "CustomParameter": {
        "fov": 0.0
      },
      "Name": "LookAtPlatformCam",
      "RotY": 49.81807,
      "ID": 3,
      "PosX": 338.16,
      "PosY": 56.45,
      "PosZ": 779.99,
      "IsDelete": false
    },
    {
      "RotX": 39.93573,
      "RotZ": 0.0,
      "Usage": "Camera",
      "LookAtCameraTemplate": null,
      "CustomParameter": {
        "fov": 0.0
      },
      "Name": "LookAtPlatformCam2",
      "RotY": 31.79433,
      "ID": 4,
      "PosX": 390.4,
      "PosY": 8.0,
      "PosZ": 810.6,
      "IsDelete": false
    },
    {
      "RotX": 42.38717,
      "RotZ": 1.6E-05,
      "Usage": "Camera",
      "LookAtCameraTemplate": null,
      "CustomParameter": {
        "fov": 45.0
      },
      "Name": "switch01cam",
      "RotY": 309.4652,
      "ID": 5,
      "PosX": 425.395,
      "PosY": 5.103313,
      "PosZ": 817.4611,
      "IsDelete": false
    }
  ],
  "MonsterList": [],
  "PropList": [
    {
      "ID": 300001,
      "PosX": 402.89999389648438,
      "PosY": -15.600000381469727,
      "PosZ": 842.5999755859375,
      "IsDelete": false,
      "Name": "Prop1",
      "RotY": 0.0,
      "RotX": 0.0,
      "RotZ": 0.0,
      "Scale": {
        "x": 1.0,
        "y": 1.0,
        "z": 1.0,
        "normalized": {
          "x": 0.577350259,
          "y": 0.577350259,
          "z": 0.577350259,
          "normalized": {
            "x": 0.5773503,
            "y": 0.5773503,
            "z": 0.5773503,
            "magnitude": 1.00000012,
            "sqrMagnitude": 1.00000024
          },
          "magnitude": 0.99999994,
          "sqrMagnitude": 0.99999994
        },
        "magnitude": 1.73205078,
        "sqrMagnitude": 3.0
      },
      "PropID": 103205,
      "LoadOnInitial": true,
      "IsOverrideInitLevelGraph": false,
      "InitLevelGraph": null,
      "ValueSource": {
        "Values": [
          {
            "Value": "LevelArea_P20331_F20331001_G13,pos1",
            "Key": "TargetAnchor1"
          },
          {
            "Value": "LevelArea_P20331_F20331001_G13,pos2",
            "Key": "TargetAnchor2"
          },
          {
            "Value": 16,
            "Key": "OnAnchor1ConnectorGroup"
          },
          {
            "Value": 17,
            "Key": "OnAnchor2ConnectorGroup"
          },
          {
            "Value": 1,
            "Key": "IsMovingPlatform"
          }
        ],
        "SharedValues": [
          {
            "Value": "LevelArea_P20331_F20331001_G13,pos1",
            "Key": "TargetAnchor1"
          },
          {
            "Value": "LevelArea_P20331_F20331001_G13,pos2",
            "Key": "TargetAnchor2"
          },
          {
            "Value": 16,
            "Key": "OnAnchor1ConnectorGroup"
          },
          {
            "Value": 17,
            "Key": "OnAnchor2ConnectorGroup"
          },
          {
            "Value": 1,
            "Key": "IsMovingPlatform"
          }
        ]
      },
      "Trigger": null,
      "CampID": 4,
      "State": "Closed",
      "EventID": 0,
      "OverrideHintRange": -1.0,
      "OverrideSoundRange": -1.0,
      "CustomTriggerMap": {},
      "CustomTriggerMapV2": {},
      "BridgeStateRotations": [],
      "AnchorGroupID": 0,
      "AnchorID": 0,
      "ChestID": 0,
      "MappingInfoID": 0,
      "SubMapID": 0,
      "DialogueTriggerAngle": 120,
      "DialogueGroups": [],
      "FirstDialogueGroupID": 0,
      "TalkDialogGroupIDList": [],
      "TalkChosenType": "undefined",
      "ServerInteractVerificationIDList": [],
      "HideInCutScene": false,
      "HideInStory": false,
      "PerformanceHideFlags": 0,
      "DisableDither": false,
      "StageObjectCapture": null,
      "RaidID": 0,
      "FarmElementID": 0,
      "CocoonID": 0,
      "ActivityMapConditionIDList": null,
      "OverrideMapIconType": -1,
      "OverrideMapStateIcons": [
        {
          "State": "Open",
          "IconID": 193,
          "Color": null,
          "AnchorKey": "LevelArea_P20331_F20331001_G13,pos2"
        },
        {
          "State": "Closed",
          "IconID": 193,
          "Color": null,
          "AnchorKey": "LevelArea_P20331_F20331001_G13,pos1"
        }
      ],
      "OverridePropName": {
        "hash": 371857150
      },
      "Dialog": null,
      "InteractIconType": "ChatMissionIcon",
      "DialogueTriggerSkipFakeAvatar": true,
      "InteractTitle": {
        "hash": 371857150
      },
      "CustomParameter": null,
      "MapCustomParameter": null,
      "NearestTeleportMappingInfoID": 0,
      "OverrideBoardShowList": null,
      "IsClientOnly": false,
      "OverrideTriggerValidGuestConfig": false,
      "TriggerValidGuest": {
        "ConfigType": "ByEntityType",
        "Npc": false,
        "NpcMonster": false,
        "LocalPlayer": true,
        "Teammember": true,
        "FakePlayer": false,
        "TargetList": null,
        "EvaluatedInstances": null
      },
      "TagOperation": "Override",
      "CameraCollisionPoint": {
        "x": 0.0,
        "y": 0.0,
        "z": 0.0,
        "magnitude": 0.0,
        "sqrMagnitude": 0.0
      },
      "CameraCenterEntityList": [],
      "IsOverrideAudioSwitch": false,
      "AudioSwitchGroupName": null,
      "AudioSwitchName": null,
      "OverrideReplaceMaterialKey": null,
      "LookAtPlayer": false,
      "LookAtPlayerTriggerRadius": 2.0,
      "SpawnConfig": {
        "OverrideSpawn": false,
        "EntitySpawnConfig": {
          "NeedBlackIn": true,
          "BlackInDistance": 25.0,
          "NeedFadeIn": true,
          "NeedFadeOut": true
        }
      }
    },
    {
      "ID": 300002,
      "PosX": 417.04998779296875,
      "PosY": -18.865329742431641,
      "PosZ": 837.54302978515625,
      "IsDelete": false,
      "Name": "switch01",
      "RotY": 1.9999999949504854E-06,
      "RotX": 0.0,
      "RotZ": 0.0,
      "Scale": {
        "x": 1.0,
        "y": 1.0,
        "z": 1.0,
        "normalized": {
          "x": 0.577350259,
          "y": 0.577350259,
          "z": 0.577350259,
          "normalized": {
            "x": 0.5773503,
            "y": 0.5773503,
            "z": 0.5773503,
            "magnitude": 1.00000012,
            "sqrMagnitude": 1.00000024
          },
          "magnitude": 0.99999994,
          "sqrMagnitude": 0.99999994
        },
        "magnitude": 1.73205078,
        "sqrMagnitude": 3.0
      },
      "PropID": 103078,
      "LoadOnInitial": true,
      "IsOverrideInitLevelGraph": false,
      "InitLevelGraph": null,
      "ValueSource": {
        "Values": [
          {
            "Value": "TriggerRoomB3MPF",
            "Key": "OnInteractTriggerCustomString"
          },
          {
            "Value": "LevelArea_P20331_F20331001_G13,switch01cam",
            "Key": "MPFVirtualCamera"
          },
          {
            "Value": 2.0,
            "Key": "DirForClose"
          },
          {
            "Value": 4.0,
            "Key": "DirForOpen"
          },
          {
            "Value": "13,300001",
            "Key": "MPFProp"
          },
          {
            "Value": "LevelArea_P20331_F20331001_G13,switch01cam",
            "Key": "LookAtAnchor"
          },
          {
            "Value": "LevelArea_P20331_F20331001_G13,LookAtPlatformCam2",
            "Key": "LookAtAnchor_Iso"
          },
          {
            "Value": 1.0,
            "Key": "UsePerspCam"
          },
          {
            "Value": "LevelArea_P20331_F20331001_G11,Cam01_followcam",
            "Key": "CaseFollowCamera"
          }
        ],
        "SharedValues": [
          {
            "Value": "TriggerRoomB3MPF",
            "Key": "OnInteractTriggerCustomString"
          },
          {
            "Value": "LevelArea_P20331_F20331001_G13,switch01cam",
            "Key": "MPFVirtualCamera"
          },
          {
            "Value": 2.0,
            "Key": "DirForClose"
          },
          {
            "Value": 4.0,
            "Key": "DirForOpen"
          },
          {
            "Value": "13,300001",
            "Key": "MPFProp"
          },
          {
            "Value": "LevelArea_P20331_F20331001_G13,switch01cam",
            "Key": "LookAtAnchor"
          },
          {
            "Value": "LevelArea_P20331_F20331001_G13,LookAtPlatformCam2",
            "Key": "LookAtAnchor_Iso"
          },
          {
            "Value": 1.0,
            "Key": "UsePerspCam"
          },
          {
            "Value": "LevelArea_P20331_F20331001_G11,Cam01_followcam",
            "Key": "CaseFollowCamera"
          }
        ]
      },
      "Trigger": null,
      "CampID": 4,
      "State": "Closed",
      "EventID": 0,
      "OverrideHintRange": -1.0,
      "OverrideSoundRange": -1.0,
      "CustomTriggerMap": {},
      "CustomTriggerMapV2": {},
      "BridgeStateRotations": [],
      "AnchorGroupID": 0,
      "AnchorID": 0,
      "ChestID": 0,
      "MappingInfoID": 0,
      "SubMapID": 0,
      "DialogueTriggerAngle": 120,
      "DialogueGroups": [],
      "FirstDialogueGroupID": 0,
      "TalkDialogGroupIDList": [],
      "TalkChosenType": "undefined",
      "ServerInteractVerificationIDList": [],
      "HideInCutScene": false,
      "HideInStory": false,
      "PerformanceHideFlags": 0,
      "DisableDither": false,
      "StageObjectCapture": null,
      "RaidID": 0,
      "FarmElementID": 0,
      "CocoonID": 0,
      "ActivityMapConditionIDList": null,
      "OverrideMapIconType": -1,
      "OverrideMapStateIcons": null,
      "OverridePropName": {
        "hash": 371857150
      },
      "Dialog": null,
      "InteractIconType": "ChatMissionIcon",
      "DialogueTriggerSkipFakeAvatar": true,
      "InteractTitle": {
        "hash": 371857150
      },
      "CustomParameter": null,
      "MapCustomParameter": null,
      "NearestTeleportMappingInfoID": 0,
      "OverrideBoardShowList": null,
      "IsClientOnly": false,
      "OverrideTriggerValidGuestConfig": false,
      "TriggerValidGuest": {
        "ConfigType": "ByEntityType",
        "Npc": false,
        "NpcMonster": false,
        "LocalPlayer": true,
        "Teammember": true,
        "FakePlayer": false,
        "TargetList": null,
        "EvaluatedInstances": null
      },
      "TagOperation": "Override",
      "CameraCollisionPoint": {
        "x": 0.0,
        "y": 0.0,
        "z": 0.0,
        "magnitude": 0.0,
        "sqrMagnitude": 0.0
      },
      "CameraCenterEntityList": [],
      "IsOverrideAudioSwitch": false,
      "AudioSwitchGroupName": null,
      "AudioSwitchName": null,
      "OverrideReplaceMaterialKey": null,
      "LookAtPlayer": false,
      "LookAtPlayerTriggerRadius": 2.0,
      "SpawnConfig": {
        "OverrideSpawn": false,
        "EntitySpawnConfig": {
          "NeedBlackIn": true,
          "BlackInDistance": 25.0,
          "NeedFadeIn": true,
          "NeedFadeOut": true
        }
      }
    },
    {
      "ID": 300003,
      "PosX": 413.70001220703125,
      "PosY": -25.57826042175293,
      "PosZ": 859.0999755859375,
      "IsDelete": false,
      "Name": "switch02",
      "RotY": 270.00009155273438,
      "RotX": 0.0,
      "RotZ": 0.0,
      "Scale": {
        "x": 1.0,
        "y": 1.0,
        "z": 1.0,
        "normalized": {
          "x": 0.577350259,
          "y": 0.577350259,
          "z": 0.577350259,
          "normalized": {
            "x": 0.5773503,
            "y": 0.5773503,
            "z": 0.5773503,
            "magnitude": 1.00000012,
            "sqrMagnitude": 1.00000024
          },
          "magnitude": 0.99999994,
          "sqrMagnitude": 0.99999994
        },
        "magnitude": 1.73205078,
        "sqrMagnitude": 3.0
      },
      "PropID": 103078,
      "LoadOnInitial": true,
      "IsOverrideInitLevelGraph": false,
      "InitLevelGraph": null,
      "ValueSource": {
        "Values": [
          {
            "Value": "TriggerRoomB3MPF",
            "Key": "OnInteractTriggerCustomString"
          },
          {
            "Value": 4.0,
            "Key": "DirForClose"
          },
          {
            "Value": 2.0,
            "Key": "DirForOpen"
          },
          {
            "Value": "13,300001",
            "Key": "MPFProp"
          },
          {
            "Value": "LevelArea_P20331_F20331001_G13,LookAtPlatformCam",
            "Key": "LookAtAnchor"
          },
          {
            "Value": "LevelArea_P20331_F20331001_G13,LookAtPlatformCam",
            "Key": "LookAtAnchor_Iso"
          },
          {
            "Value": "LevelArea_P20331_F20331001_G11,Cam01_followcam",
            "Key": "CaseFollowCamera"
          }
        ],
        "SharedValues": [
          {
            "Value": "TriggerRoomB3MPF",
            "Key": "OnInteractTriggerCustomString"
          },
          {
            "Value": 4.0,
            "Key": "DirForClose"
          },
          {
            "Value": 2.0,
            "Key": "DirForOpen"
          },
          {
            "Value": "13,300001",
            "Key": "MPFProp"
          },
          {
            "Value": "LevelArea_P20331_F20331001_G13,LookAtPlatformCam",
            "Key": "LookAtAnchor"
          },
          {
            "Value": "LevelArea_P20331_F20331001_G13,LookAtPlatformCam",
            "Key": "LookAtAnchor_Iso"
          },
          {
            "Value": "LevelArea_P20331_F20331001_G11,Cam01_followcam",
            "Key": "CaseFollowCamera"
          }
        ]
      },
      "Trigger": null,
      "CampID": 4,
      "State": "Closed",
      "EventID": 0,
      "OverrideHintRange": -1.0,
      "OverrideSoundRange": -1.0,
      "CustomTriggerMap": {},
      "CustomTriggerMapV2": {},
      "BridgeStateRotations": [],
      "AnchorGroupID": 0,
      "AnchorID": 0,
      "ChestID": 0,
      "MappingInfoID": 0,
      "SubMapID": 0,
      "DialogueTriggerAngle": 120,
      "DialogueGroups": [],
      "FirstDialogueGroupID": 0,
      "TalkDialogGroupIDList": [],
      "TalkChosenType": "undefined",
      "ServerInteractVerificationIDList": [],
      "HideInCutScene": false,
      "HideInStory": false,
      "PerformanceHideFlags": 0,
      "DisableDither": false,
      "StageObjectCapture": null,
      "RaidID": 0,
      "FarmElementID": 0,
      "CocoonID": 0,
      "ActivityMapConditionIDList": null,
      "OverrideMapIconType": -1,
      "OverrideMapStateIcons": null,
      "OverridePropName": {
        "hash": 371857150
      },
      "Dialog": null,
      "InteractIconType": "ChatMissionIcon",
      "DialogueTriggerSkipFakeAvatar": true,
      "InteractTitle": {
        "hash": 371857150
      },
      "CustomParameter": null,
      "MapCustomParameter": null,
      "NearestTeleportMappingInfoID": 0,
      "OverrideBoardShowList": null,
      "IsClientOnly": false,
      "OverrideTriggerValidGuestConfig": false,
      "TriggerValidGuest": {
        "ConfigType": "ByEntityType",
        "Npc": false,
        "NpcMonster": false,
        "LocalPlayer": true,
        "Teammember": true,
        "FakePlayer": false,
        "TargetList": null,
        "EvaluatedInstances": null
      },
      "TagOperation": "Override",
      "CameraCollisionPoint": {
        "x": 0.0,
        "y": 0.0,
        "z": 0.0,
        "magnitude": 0.0,
        "sqrMagnitude": 0.0
      },
      "CameraCenterEntityList": [],
      "IsOverrideAudioSwitch": false,
      "AudioSwitchGroupName": null,
      "AudioSwitchName": null,
      "OverrideReplaceMaterialKey": null,
      "LookAtPlayer": false,
      "LookAtPlayerTriggerRadius": 2.0,
      "SpawnConfig": {
        "OverrideSpawn": false,
        "EntitySpawnConfig": {
          "NeedBlackIn": true,
          "BlackInDistance": 25.0,
          "NeedFadeIn": true,
          "NeedFadeOut": true
        }
      }
    },
    {
      "ID": 300006,
      "PosX": 405.35699462890625,
      "PosY": -16.086999893188477,
      "PosZ": 823.70001220703125,
      "IsDelete": false,
      "Name": "Anchor1_Iso_Eff_01",
      "RotY": 90.0,
      "RotX": 0.0,
      "RotZ": 0.0,
      "Scale": {
        "x": 1.0,
        "y": 1.0,
        "z": 1.0,
        "normalized": {
          "x": 0.577350259,
          "y": 0.577350259,
          "z": 0.577350259,
          "normalized": {
            "x": 0.5773503,
            "y": 0.5773503,
            "z": 0.5773503,
            "magnitude": 1.00000012,
            "sqrMagnitude": 1.00000024
          },
          "magnitude": 0.99999994,
          "sqrMagnitude": 0.99999994
        },
        "magnitude": 1.73205078,
        "sqrMagnitude": 3.0
      },
      "PropID": 103085,
      "LoadOnInitial": true,
      "IsOverrideInitLevelGraph": false,
      "InitLevelGraph": null,
      "ValueSource": {
        "Values": [
          {
            "Value": "EffectEmit_OnAnchor1_Case1",
            "Key": "GroupEventStringForEmit"
          }
        ],
        "SharedValues": [
          {
            "Value": "EffectEmit_OnAnchor1_Case1",
            "Key": "GroupEventStringForEmit"
          }
        ]
      },
      "Trigger": null,
      "CampID": 4,
      "State": "Closed",
      "EventID": 0,
      "OverrideHintRange": -1.0,
      "OverrideSoundRange": -1.0,
      "CustomTriggerMap": {},
      "CustomTriggerMapV2": {},
      "BridgeStateRotations": [],
      "AnchorGroupID": 0,
      "AnchorID": 0,
      "ChestID": 0,
      "MappingInfoID": 0,
      "SubMapID": 0,
      "DialogueTriggerAngle": 120,
      "DialogueGroups": [],
      "FirstDialogueGroupID": 0,
      "TalkDialogGroupIDList": [],
      "TalkChosenType": "undefined",
      "ServerInteractVerificationIDList": [],
      "HideInCutScene": false,
      "HideInStory": false,
      "PerformanceHideFlags": 0,
      "DisableDither": false,
      "StageObjectCapture": null,
      "RaidID": 0,
      "FarmElementID": 0,
      "CocoonID": 0,
      "ActivityMapConditionIDList": null,
      "OverrideMapIconType": -1,
      "OverrideMapStateIcons": null,
      "OverridePropName": {
        "hash": 371857150
      },
      "Dialog": null,
      "InteractIconType": "ChatMissionIcon",
      "DialogueTriggerSkipFakeAvatar": true,
      "InteractTitle": {
        "hash": 371857150
      },
      "CustomParameter": null,
      "MapCustomParameter": null,
      "NearestTeleportMappingInfoID": 0,
      "OverrideBoardShowList": null,
      "IsClientOnly": false,
      "OverrideTriggerValidGuestConfig": false,
      "TriggerValidGuest": {
        "ConfigType": "ByEntityType",
        "Npc": false,
        "NpcMonster": false,
        "LocalPlayer": true,
        "Teammember": true,
        "FakePlayer": false,
        "TargetList": null,
        "EvaluatedInstances": null
      },
      "TagOperation": "Override",
      "CameraCollisionPoint": {
        "x": 0.0,
        "y": 0.0,
        "z": 0.0,
        "magnitude": 0.0,
        "sqrMagnitude": 0.0
      },
      "CameraCenterEntityList": [],
      "IsOverrideAudioSwitch": false,
      "AudioSwitchGroupName": null,
      "AudioSwitchName": null,
      "OverrideReplaceMaterialKey": null,
      "LookAtPlayer": false,
      "LookAtPlayerTriggerRadius": 2.0,
      "SpawnConfig": {
        "OverrideSpawn": false,
        "EntitySpawnConfig": {
          "NeedBlackIn": true,
          "BlackInDistance": 25.0,
          "NeedFadeIn": true,
          "NeedFadeOut": true
        }
      }
    },
    {
      "ID": 300004,
      "PosX": 412.11099243164063,
      "PosY": -25.429000854492188,
      "PosZ": 856.20001220703125,
      "IsDelete": false,
      "Name": "Anchor2_Iso_Eff_01",
      "RotY": 0.0,
      "RotX": 0.0,
      "RotZ": 0.0,
      "Scale": {
        "x": 1.0,
        "y": 1.0,
        "z": 1.0,
        "normalized": {
          "x": 0.577350259,
          "y": 0.577350259,
          "z": 0.577350259,
          "normalized": {
            "x": 0.5773503,
            "y": 0.5773503,
            "z": 0.5773503,
            "magnitude": 1.00000012,
            "sqrMagnitude": 1.00000024
          },
          "magnitude": 0.99999994,
          "sqrMagnitude": 0.99999994
        },
        "magnitude": 1.73205078,
        "sqrMagnitude": 3.0
      },
      "PropID": 103085,
      "LoadOnInitial": true,
      "IsOverrideInitLevelGraph": false,
      "InitLevelGraph": null,
      "ValueSource": {
        "Values": [
          {
            "Value": "EffectEmit_OnAnchor2_Case1",
            "Key": "GroupEventStringForEmit"
          }
        ],
        "SharedValues": [
          {
            "Value": "EffectEmit_OnAnchor2_Case1",
            "Key": "GroupEventStringForEmit"
          }
        ]
      },
      "Trigger": null,
      "CampID": 4,
      "State": "Closed",
      "EventID": 0,
      "OverrideHintRange": -1.0,
      "OverrideSoundRange": -1.0,
      "CustomTriggerMap": {},
      "CustomTriggerMapV2": {},
      "BridgeStateRotations": [],
      "AnchorGroupID": 0,
      "AnchorID": 0,
      "ChestID": 0,
      "MappingInfoID": 0,
      "SubMapID": 0,
      "DialogueTriggerAngle": 120,
      "DialogueGroups": [],
      "FirstDialogueGroupID": 0,
      "TalkDialogGroupIDList": [],
      "TalkChosenType": "undefined",
      "ServerInteractVerificationIDList": [],
      "HideInCutScene": false,
      "HideInStory": false,
      "PerformanceHideFlags": 0,
      "DisableDither": false,
      "StageObjectCapture": null,
      "RaidID": 0,
      "FarmElementID": 0,
      "CocoonID": 0,
      "ActivityMapConditionIDList": null,
      "OverrideMapIconType": -1,
      "OverrideMapStateIcons": null,
      "OverridePropName": {
        "hash": 371857150
      },
      "Dialog": null,
      "InteractIconType": "ChatMissionIcon",
      "DialogueTriggerSkipFakeAvatar": true,
      "InteractTitle": {
        "hash": 371857150
      },
      "CustomParameter": null,
      "MapCustomParameter": null,
      "NearestTeleportMappingInfoID": 0,
      "OverrideBoardShowList": null,
      "IsClientOnly": false,
      "OverrideTriggerValidGuestConfig": false,
      "TriggerValidGuest": {
        "ConfigType": "ByEntityType",
        "Npc": false,
        "NpcMonster": false,
        "LocalPlayer": true,
        "Teammember": true,
        "FakePlayer": false,
        "TargetList": null,
        "EvaluatedInstances": null
      },
      "TagOperation": "Override",
      "CameraCollisionPoint": {
        "x": 0.0,
        "y": 0.0,
        "z": 0.0,
        "magnitude": 0.0,
        "sqrMagnitude": 0.0
      },
      "CameraCenterEntityList": [],
      "IsOverrideAudioSwitch": false,
      "AudioSwitchGroupName": null,
      "AudioSwitchName": null,
      "OverrideReplaceMaterialKey": null,
      "LookAtPlayer": false,
      "LookAtPlayerTriggerRadius": 2.0,
      "SpawnConfig": {
        "OverrideSpawn": false,
        "EntitySpawnConfig": {
          "NeedBlackIn": true,
          "BlackInDistance": 25.0,
          "NeedFadeIn": true,
          "NeedFadeOut": true
        }
      }
    },
    {
      "ID": 300005,
      "PosX": 405.8599853515625,
      "PosY": -16.076000213623047,
      "PosZ": 839.96002197265625,
      "IsDelete": false,
      "Name": "Anchor2_Iso_Eff_02",
      "RotY": 90.0,
      "RotX": 0.0,
      "RotZ": 0.0,
      "Scale": {
        "x": 1.0,
        "y": 1.0,
        "z": 1.0,
        "normalized": {
          "x": 0.577350259,
          "y": 0.577350259,
          "z": 0.577350259,
          "normalized": {
            "x": 0.5773503,
            "y": 0.5773503,
            "z": 0.5773503,
            "magnitude": 1.00000012,
            "sqrMagnitude": 1.00000024
          },
          "magnitude": 0.99999994,
          "sqrMagnitude": 0.99999994
        },
        "magnitude": 1.73205078,
        "sqrMagnitude": 3.0
      },
      "PropID": 103085,
      "LoadOnInitial": true,
      "IsOverrideInitLevelGraph": false,
      "InitLevelGraph": null,
      "ValueSource": {
        "Values": [
          {
            "Value": "EffectEmit_OnAnchor2_Case1",
            "Key": "GroupEventStringForEmit"
          }
        ],
        "SharedValues": [
          {
            "Value": "EffectEmit_OnAnchor2_Case1",
            "Key": "GroupEventStringForEmit"
          }
        ]
      },
      "Trigger": null,
      "CampID": 4,
      "State": "Closed",
      "EventID": 0,
      "OverrideHintRange": -1.0,
      "OverrideSoundRange": -1.0,
      "CustomTriggerMap": {},
      "CustomTriggerMapV2": {},
      "BridgeStateRotations": [],
      "AnchorGroupID": 0,
      "AnchorID": 0,
      "ChestID": 0,
      "MappingInfoID": 0,
      "SubMapID": 0,
      "DialogueTriggerAngle": 120,
      "DialogueGroups": [],
      "FirstDialogueGroupID": 0,
      "TalkDialogGroupIDList": [],
      "TalkChosenType": "undefined",
      "ServerInteractVerificationIDList": [],
      "HideInCutScene": false,
      "HideInStory": false,
      "PerformanceHideFlags": 0,
      "DisableDither": false,
      "StageObjectCapture": null,
      "RaidID": 0,
      "FarmElementID": 0,
      "CocoonID": 0,
      "ActivityMapConditionIDList": null,
      "OverrideMapIconType": -1,
      "OverrideMapStateIcons": null,
      "OverridePropName": {
        "hash": 371857150
      },
      "Dialog": null,
      "InteractIconType": "ChatMissionIcon",
      "DialogueTriggerSkipFakeAvatar": true,
      "InteractTitle": {
        "hash": 371857150
      },
      "CustomParameter": null,
      "MapCustomParameter": null,
      "NearestTeleportMappingInfoID": 0,
      "OverrideBoardShowList": null,
      "IsClientOnly": false,
      "OverrideTriggerValidGuestConfig": false,
      "TriggerValidGuest": {
        "ConfigType": "ByEntityType",
        "Npc": false,
        "NpcMonster": false,
        "LocalPlayer": true,
        "Teammember": true,
        "FakePlayer": false,
        "TargetList": null,
        "EvaluatedInstances": null
      },
      "TagOperation": "Override",
      "CameraCollisionPoint": {
        "x": 0.0,
        "y": 0.0,
        "z": 0.0,
        "magnitude": 0.0,
        "sqrMagnitude": 0.0
      },
      "CameraCenterEntityList": [],
      "IsOverrideAudioSwitch": false,
      "AudioSwitchGroupName": null,
      "AudioSwitchName": null,
      "OverrideReplaceMaterialKey": null,
      "LookAtPlayer": false,
      "LookAtPlayerTriggerRadius": 2.0,
      "SpawnConfig": {
        "OverrideSpawn": false,
        "EntitySpawnConfig": {
          "NeedBlackIn": true,
          "BlackInDistance": 25.0,
          "NeedFadeIn": true,
          "NeedFadeOut": true
        }
      }
    },
    {
      "ID": 300007,
      "PosX": 402.6400146484375,
      "PosY": -15.770000457763672,
      "PosZ": 828.15997314453125,
      "IsDelete": false,
      "Name": "TraclSohm_Eff_01",
      "RotY": 180.0,
      "RotX": 0.0,
      "RotZ": 0.0,
      "Scale": {
        "x": 1.0,
        "y": 1.0,
        "z": 2.191644,
        "normalized": {
          "x": 0.383389384,
          "y": 0.383389384,
          "z": 0.840253,
          "magnitude": 1.0,
          "sqrMagnitude": 1.0
        },
        "magnitude": 2.60831428,
        "sqrMagnitude": 6.80330324
      },
      "PropID": 103092,
      "LoadOnInitial": true,
      "IsOverrideInitLevelGraph": false,
      "InitLevelGraph": null,
      "ValueSource": {
        "Values": [
          {
            "Value": "EffectOpen_OnAnchor1_Case1",
            "Key": "GroupEventStringForOpen"
          },
          {
            "Value": "EffectClose_OnAnchor",
            "Key": "GroupEventStringForClose"
          }
        ],
        "SharedValues": [
          {
            "Value": "EffectOpen_OnAnchor1_Case1",
            "Key": "GroupEventStringForOpen"
          },
          {
            "Value": "EffectClose_OnAnchor",
            "Key": "GroupEventStringForClose"
          }
        ]
      },
      "Trigger": null,
      "CampID": 4,
      "State": "Closed",
      "EventID": 0,
      "OverrideHintRange": -1.0,
      "OverrideSoundRange": -1.0,
      "CustomTriggerMap": {},
      "CustomTriggerMapV2": {},
      "BridgeStateRotations": [],
      "AnchorGroupID": 0,
      "AnchorID": 0,
      "ChestID": 0,
      "MappingInfoID": 0,
      "SubMapID": 0,
      "DialogueTriggerAngle": 120,
      "DialogueGroups": [],
      "FirstDialogueGroupID": 0,
      "TalkDialogGroupIDList": [],
      "TalkChosenType": "undefined",
      "ServerInteractVerificationIDList": [],
      "HideInCutScene": false,
      "HideInStory": false,
      "PerformanceHideFlags": 0,
      "DisableDither": false,
      "StageObjectCapture": null,
      "RaidID": 0,
      "FarmElementID": 0,
      "CocoonID": 0,
      "ActivityMapConditionIDList": null,
      "OverrideMapIconType": -1,
      "OverrideMapStateIcons": null,
      "OverridePropName": {
        "hash": 371857150
      },
      "Dialog": null,
      "InteractIconType": "ChatMissionIcon",
      "DialogueTriggerSkipFakeAvatar": true,
      "InteractTitle": {
        "hash": 371857150
      },
      "CustomParameter": null,
      "MapCustomParameter": null,
      "NearestTeleportMappingInfoID": 0,
      "OverrideBoardShowList": null,
      "IsClientOnly": false,
      "OverrideTriggerValidGuestConfig": false,
      "TriggerValidGuest": {
        "ConfigType": "ByEntityType",
        "Npc": false,
        "NpcMonster": false,
        "LocalPlayer": true,
        "Teammember": true,
        "FakePlayer": false,
        "TargetList": null,
        "EvaluatedInstances": null
      },
      "TagOperation": "Override",
      "CameraCollisionPoint": {
        "x": 0.0,
        "y": 0.0,
        "z": 0.0,
        "magnitude": 0.0,
        "sqrMagnitude": 0.0
      },
      "CameraCenterEntityList": [],
      "IsOverrideAudioSwitch": false,
      "AudioSwitchGroupName": null,
      "AudioSwitchName": null,
      "OverrideReplaceMaterialKey": null,
      "LookAtPlayer": false,
      "LookAtPlayerTriggerRadius": 2.0,
      "SpawnConfig": {
        "OverrideSpawn": false,
        "EntitySpawnConfig": {
          "NeedBlackIn": true,
          "BlackInDistance": 25.0,
          "NeedFadeIn": true,
          "NeedFadeOut": true
        }
      }
    },
    {
      "ID": 300008,
      "PosX": 402.6400146484375,
      "PosY": -15.770000457763672,
      "PosZ": 828.15997314453125,
      "IsDelete": false,
      "Name": "TraclSohm_Eff_02",
      "RotY": 0.0,
      "RotX": 0.0,
      "RotZ": 0.0,
      "Scale": {
        "x": 1.0,
        "y": 1.0,
        "z": 2.191644,
        "normalized": {
          "x": 0.383389384,
          "y": 0.383389384,
          "z": 0.840253,
          "magnitude": 1.0,
          "sqrMagnitude": 1.0
        },
        "magnitude": 2.60831428,
        "sqrMagnitude": 6.80330324
      },
      "PropID": 103092,
      "LoadOnInitial": true,
      "IsOverrideInitLevelGraph": false,
      "InitLevelGraph": null,
      "ValueSource": {
        "Values": [
          {
            "Value": "EffectOpen_OnAnchor2_Case1",
            "Key": "GroupEventStringForOpen"
          },
          {
            "Value": "EffectClose_OnAnchor",
            "Key": "GroupEventStringForClose"
          }
        ],
        "SharedValues": [
          {
            "Value": "EffectOpen_OnAnchor2_Case1",
            "Key": "GroupEventStringForOpen"
          },
          {
            "Value": "EffectClose_OnAnchor",
            "Key": "GroupEventStringForClose"
          }
        ]
      },
      "Trigger": null,
      "CampID": 4,
      "State": "Closed",
      "EventID": 0,
      "OverrideHintRange": -1.0,
      "OverrideSoundRange": -1.0,
      "CustomTriggerMap": {},
      "CustomTriggerMapV2": {},
      "BridgeStateRotations": [],
      "AnchorGroupID": 0,
      "AnchorID": 0,
      "ChestID": 0,
      "MappingInfoID": 0,
      "SubMapID": 0,
      "DialogueTriggerAngle": 120,
      "DialogueGroups": [],
      "FirstDialogueGroupID": 0,
      "TalkDialogGroupIDList": [],
      "TalkChosenType": "undefined",
      "ServerInteractVerificationIDList": [],
      "HideInCutScene": false,
      "HideInStory": false,
      "PerformanceHideFlags": 0,
      "DisableDither": false,
      "StageObjectCapture": null,
      "RaidID": 0,
      "FarmElementID": 0,
      "CocoonID": 0,
      "ActivityMapConditionIDList": null,
      "OverrideMapIconType": -1,
      "OverrideMapStateIcons": null,
      "OverridePropName": {
        "hash": 371857150
      },
      "Dialog": null,
      "InteractIconType": "ChatMissionIcon",
      "DialogueTriggerSkipFakeAvatar": true,
      "InteractTitle": {
        "hash": 371857150
      },
      "CustomParameter": null,
      "MapCustomParameter": null,
      "NearestTeleportMappingInfoID": 0,
      "OverrideBoardShowList": null,
      "IsClientOnly": false,
      "OverrideTriggerValidGuestConfig": false,
      "TriggerValidGuest": {
        "ConfigType": "ByEntityType",
        "Npc": false,
        "NpcMonster": false,
        "LocalPlayer": true,
        "Teammember": true,
        "FakePlayer": false,
        "TargetList": null,
        "EvaluatedInstances": null
      },
      "TagOperation": "Override",
      "CameraCollisionPoint": {
        "x": 0.0,
        "y": 0.0,
        "z": 0.0,
        "magnitude": 0.0,
        "sqrMagnitude": 0.0
      },
      "CameraCenterEntityList": [],
      "IsOverrideAudioSwitch": false,
      "AudioSwitchGroupName": null,
      "AudioSwitchName": null,
      "OverrideReplaceMaterialKey": null,
      "LookAtPlayer": false,
      "LookAtPlayerTriggerRadius": 2.0,
      "SpawnConfig": {
        "OverrideSpawn": false,
        "EntitySpawnConfig": {
          "NeedBlackIn": true,
          "BlackInDistance": 25.0,
          "NeedFadeIn": true,
          "NeedFadeOut": true
        }
      }
    },
    {
      "ID": 300009,
      "PosX": 405.35699462890625,
      "PosY": -16.086999893188477,
      "PosZ": 823.70001220703125,
      "IsDelete": false,
      "Name": "Cam02_Anchor1_Iso_Eff_01",
      "RotY": 90.0,
      "RotX": 0.0,
      "RotZ": 0.0,
      "Scale": {
        "x": 1.0,
        "y": 1.0,
        "z": 1.0,
        "normalized": {
          "x": 0.577350259,
          "y": 0.577350259,
          "z": 0.577350259,
          "normalized": {
            "x": 0.5773503,
            "y": 0.5773503,
            "z": 0.5773503,
            "magnitude": 1.00000012,
            "sqrMagnitude": 1.00000024
          },
          "magnitude": 0.99999994,
          "sqrMagnitude": 0.99999994
        },
        "magnitude": 1.73205078,
        "sqrMagnitude": 3.0
      },
      "PropID": 103085,
      "LoadOnInitial": true,
      "IsOverrideInitLevelGraph": false,
      "InitLevelGraph": null,
      "ValueSource": {
        "Values": [
          {
            "Value": "EffectEmit_OnAnchor1_Case2",
            "Key": "GroupEventStringForEmit"
          }
        ],
        "SharedValues": [
          {
            "Value": "EffectEmit_OnAnchor1_Case2",
            "Key": "GroupEventStringForEmit"
          }
        ]
      },
      "Trigger": null,
      "CampID": 4,
      "State": "Closed",
      "EventID": 0,
      "OverrideHintRange": -1.0,
      "OverrideSoundRange": -1.0,
      "CustomTriggerMap": {},
      "CustomTriggerMapV2": {},
      "BridgeStateRotations": [],
      "AnchorGroupID": 0,
      "AnchorID": 0,
      "ChestID": 0,
      "MappingInfoID": 0,
      "SubMapID": 0,
      "DialogueTriggerAngle": 120,
      "DialogueGroups": [],
      "FirstDialogueGroupID": 0,
      "TalkDialogGroupIDList": [],
      "TalkChosenType": "undefined",
      "ServerInteractVerificationIDList": [],
      "HideInCutScene": false,
      "HideInStory": false,
      "PerformanceHideFlags": 0,
      "DisableDither": false,
      "StageObjectCapture": null,
      "RaidID": 0,
      "FarmElementID": 0,
      "CocoonID": 0,
      "ActivityMapConditionIDList": null,
      "OverrideMapIconType": -1,
      "OverrideMapStateIcons": null,
      "OverridePropName": {
        "hash": 371857150
      },
      "Dialog": null,
      "InteractIconType": "ChatMissionIcon",
      "DialogueTriggerSkipFakeAvatar": true,
      "InteractTitle": {
        "hash": 371857150
      },
      "CustomParameter": null,
      "MapCustomParameter": null,
      "NearestTeleportMappingInfoID": 0,
      "OverrideBoardShowList": null,
      "IsClientOnly": false,
      "OverrideTriggerValidGuestConfig": false,
      "TriggerValidGuest": {
        "ConfigType": "ByEntityType",
        "Npc": false,
        "NpcMonster": false,
        "LocalPlayer": true,
        "Teammember": true,
        "FakePlayer": false,
        "TargetList": null,
        "EvaluatedInstances": null
      },
      "TagOperation": "Override",
      "CameraCollisionPoint": {
        "x": 0.0,
        "y": 0.0,
        "z": 0.0,
        "magnitude": 0.0,
        "sqrMagnitude": 0.0
      },
      "CameraCenterEntityList": [],
      "IsOverrideAudioSwitch": false,
      "AudioSwitchGroupName": null,
      "AudioSwitchName": null,
      "OverrideReplaceMaterialKey": null,
      "LookAtPlayer": false,
      "LookAtPlayerTriggerRadius": 2.0,
      "SpawnConfig": {
        "OverrideSpawn": false,
        "EntitySpawnConfig": {
          "NeedBlackIn": true,
          "BlackInDistance": 25.0,
          "NeedFadeIn": true,
          "NeedFadeOut": true
        }
      }
    },
    {
      "ID": 300010,
      "PosX": 405.8599853515625,
      "PosY": -16.076000213623047,
      "PosZ": 839.96002197265625,
      "IsDelete": false,
      "Name": "Cam02_Anchor2_Iso_Eff_02",
      "RotY": 90.0,
      "RotX": 0.0,
      "RotZ": 0.0,
      "Scale": {
        "x": 1.0,
        "y": 1.0,
        "z": 1.0,
        "normalized": {
          "x": 0.577350259,
          "y": 0.577350259,
          "z": 0.577350259,
          "normalized": {
            "x": 0.5773503,
            "y": 0.5773503,
            "z": 0.5773503,
            "magnitude": 1.00000012,
            "sqrMagnitude": 1.00000024
          },
          "magnitude": 0.99999994,
          "sqrMagnitude": 0.99999994
        },
        "magnitude": 1.73205078,
        "sqrMagnitude": 3.0
      },
      "PropID": 103085,
      "LoadOnInitial": true,
      "IsOverrideInitLevelGraph": false,
      "InitLevelGraph": null,
      "ValueSource": {
        "Values": [
          {
            "Value": "EffectEmit_OnAnchor2_Case2",
            "Key": "GroupEventStringForEmit"
          }
        ],
        "SharedValues": [
          {
            "Value": "EffectEmit_OnAnchor2_Case2",
            "Key": "GroupEventStringForEmit"
          }
        ]
      },
      "Trigger": null,
      "CampID": 4,
      "State": "Closed",
      "EventID": 0,
      "OverrideHintRange": -1.0,
      "OverrideSoundRange": -1.0,
      "CustomTriggerMap": {},
      "CustomTriggerMapV2": {},
      "BridgeStateRotations": [],
      "AnchorGroupID": 0,
      "AnchorID": 0,
      "ChestID": 0,
      "MappingInfoID": 0,
      "SubMapID": 0,
      "DialogueTriggerAngle": 120,
      "DialogueGroups": [],
      "FirstDialogueGroupID": 0,
      "TalkDialogGroupIDList": [],
      "TalkChosenType": "undefined",
      "ServerInteractVerificationIDList": [],
      "HideInCutScene": false,
      "HideInStory": false,
      "PerformanceHideFlags": 0,
      "DisableDither": false,
      "StageObjectCapture": null,
      "RaidID": 0,
      "FarmElementID": 0,
      "CocoonID": 0,
      "ActivityMapConditionIDList": null,
      "OverrideMapIconType": -1,
      "OverrideMapStateIcons": null,
      "OverridePropName": {
        "hash": 371857150
      },
      "Dialog": null,
      "InteractIconType": "ChatMissionIcon",
      "DialogueTriggerSkipFakeAvatar": true,
      "InteractTitle": {
        "hash": 371857150
      },
      "CustomParameter": null,
      "MapCustomParameter": null,
      "NearestTeleportMappingInfoID": 0,
      "OverrideBoardShowList": null,
      "IsClientOnly": false,
      "OverrideTriggerValidGuestConfig": false,
      "TriggerValidGuest": {
        "ConfigType": "ByEntityType",
        "Npc": false,
        "NpcMonster": false,
        "LocalPlayer": true,
        "Teammember": true,
        "FakePlayer": false,
        "TargetList": null,
        "EvaluatedInstances": null
      },
      "TagOperation": "Override",
      "CameraCollisionPoint": {
        "x": 0.0,
        "y": 0.0,
        "z": 0.0,
        "magnitude": 0.0,
        "sqrMagnitude": 0.0
      },
      "CameraCenterEntityList": [],
      "IsOverrideAudioSwitch": false,
      "AudioSwitchGroupName": null,
      "AudioSwitchName": null,
      "OverrideReplaceMaterialKey": null,
      "LookAtPlayer": false,
      "LookAtPlayerTriggerRadius": 2.0,
      "SpawnConfig": {
        "OverrideSpawn": false,
        "EntitySpawnConfig": {
          "NeedBlackIn": true,
          "BlackInDistance": 25.0,
          "NeedFadeIn": true,
          "NeedFadeOut": true
        }
      }
    },
    {
      "ID": 300011,
      "PosX": 402.6400146484375,
      "PosY": -15.770000457763672,
      "PosZ": 828.15997314453125,
      "IsDelete": false,
      "Name": "Cam02_TraclSohm_Eff_01",
      "RotY": 180.0,
      "RotX": 0.0,
      "RotZ": 0.0,
      "Scale": {
        "x": 1.0,
        "y": 1.0,
        "z": 1.55,
        "normalized": {
          "x": 0.476595879,
          "y": 0.476595879,
          "z": 0.7387236,
          "normalized": {
            "x": 0.476595938,
            "y": 0.476595938,
            "z": 0.738723636,
            "magnitude": 1.0,
            "sqrMagnitude": 1.0
          },
          "magnitude": 0.9999999,
          "sqrMagnitude": 0.999999762
        },
        "magnitude": 2.09821367,
        "sqrMagnitude": 4.4025
      },
      "PropID": 103092,
      "LoadOnInitial": true,
      "IsOverrideInitLevelGraph": false,
      "InitLevelGraph": null,
      "ValueSource": {
        "Values": [
          {
            "Value": "EffectOpen_OnAnchor1_Case2",
            "Key": "GroupEventStringForOpen"
          },
          {
            "Value": "EffectClose_OnAnchor",
            "Key": "GroupEventStringForClose"
          }
        ],
        "SharedValues": [
          {
            "Value": "EffectOpen_OnAnchor1_Case2",
            "Key": "GroupEventStringForOpen"
          },
          {
            "Value": "EffectClose_OnAnchor",
            "Key": "GroupEventStringForClose"
          }
        ]
      },
      "Trigger": null,
      "CampID": 4,
      "State": "Closed",
      "EventID": 0,
      "OverrideHintRange": -1.0,
      "OverrideSoundRange": -1.0,
      "CustomTriggerMap": {},
      "CustomTriggerMapV2": {},
      "BridgeStateRotations": [],
      "AnchorGroupID": 0,
      "AnchorID": 0,
      "ChestID": 0,
      "MappingInfoID": 0,
      "SubMapID": 0,
      "DialogueTriggerAngle": 120,
      "DialogueGroups": [],
      "FirstDialogueGroupID": 0,
      "TalkDialogGroupIDList": [],
      "TalkChosenType": "undefined",
      "ServerInteractVerificationIDList": [],
      "HideInCutScene": false,
      "HideInStory": false,
      "PerformanceHideFlags": 0,
      "DisableDither": false,
      "StageObjectCapture": null,
      "RaidID": 0,
      "FarmElementID": 0,
      "CocoonID": 0,
      "ActivityMapConditionIDList": null,
      "OverrideMapIconType": -1,
      "OverrideMapStateIcons": null,
      "OverridePropName": {
        "hash": 371857150
      },
      "Dialog": null,
      "InteractIconType": "ChatMissionIcon",
      "DialogueTriggerSkipFakeAvatar": true,
      "InteractTitle": {
        "hash": 371857150
      },
      "CustomParameter": null,
      "MapCustomParameter": null,
      "NearestTeleportMappingInfoID": 0,
      "OverrideBoardShowList": null,
      "IsClientOnly": false,
      "OverrideTriggerValidGuestConfig": false,
      "TriggerValidGuest": {
        "ConfigType": "ByEntityType",
        "Npc": false,
        "NpcMonster": false,
        "LocalPlayer": true,
        "Teammember": true,
        "FakePlayer": false,
        "TargetList": null,
        "EvaluatedInstances": null
      },
      "TagOperation": "Override",
      "CameraCollisionPoint": {
        "x": 0.0,
        "y": 0.0,
        "z": 0.0,
        "magnitude": 0.0,
        "sqrMagnitude": 0.0
      },
      "CameraCenterEntityList": [],
      "IsOverrideAudioSwitch": false,
      "AudioSwitchGroupName": null,
      "AudioSwitchName": null,
      "OverrideReplaceMaterialKey": null,
      "LookAtPlayer": false,
      "LookAtPlayerTriggerRadius": 2.0,
      "SpawnConfig": {
        "OverrideSpawn": false,
        "EntitySpawnConfig": {
          "NeedBlackIn": true,
          "BlackInDistance": 25.0,
          "NeedFadeIn": true,
          "NeedFadeOut": true
        }
      }
    },
    {
      "ID": 300012,
      "PosX": 402.6400146484375,
      "PosY": -15.770000457763672,
      "PosZ": 828.15997314453125,
      "IsDelete": false,
      "Name": "Cam02_TraclSohm_Eff_02",
      "RotY": 0.0,
      "RotX": 0.0,
      "RotZ": 0.0,
      "Scale": {
        "x": 1.0,
        "y": 1.0,
        "z": 1.55,
        "normalized": {
          "x": 0.476595879,
          "y": 0.476595879,
          "z": 0.7387236,
          "normalized": {
            "x": 0.476595938,
            "y": 0.476595938,
            "z": 0.738723636,
            "magnitude": 1.0,
            "sqrMagnitude": 1.0
          },
          "magnitude": 0.9999999,
          "sqrMagnitude": 0.999999762
        },
        "magnitude": 2.09821367,
        "sqrMagnitude": 4.4025
      },
      "PropID": 103092,
      "LoadOnInitial": true,
      "IsOverrideInitLevelGraph": false,
      "InitLevelGraph": null,
      "ValueSource": {
        "Values": [
          {
            "Value": "EffectOpen_OnAnchor2_Case2",
            "Key": "GroupEventStringForOpen"
          },
          {
            "Value": "EffectClose_OnAnchor",
            "Key": "GroupEventStringForClose"
          }
        ],
        "SharedValues": [
          {
            "Value": "EffectOpen_OnAnchor2_Case2",
            "Key": "GroupEventStringForOpen"
          },
          {
            "Value": "EffectClose_OnAnchor",
            "Key": "GroupEventStringForClose"
          }
        ]
      },
      "Trigger": null,
      "CampID": 4,
      "State": "Closed",
      "EventID": 0,
      "OverrideHintRange": -1.0,
      "OverrideSoundRange": -1.0,
      "CustomTriggerMap": {},
      "CustomTriggerMapV2": {},
      "BridgeStateRotations": [],
      "AnchorGroupID": 0,
      "AnchorID": 0,
      "ChestID": 0,
      "MappingInfoID": 0,
      "SubMapID": 0,
      "DialogueTriggerAngle": 120,
      "DialogueGroups": [],
      "FirstDialogueGroupID": 0,
      "TalkDialogGroupIDList": [],
      "TalkChosenType": "undefined",
      "ServerInteractVerificationIDList": [],
      "HideInCutScene": false,
      "HideInStory": false,
      "PerformanceHideFlags": 0,
      "DisableDither": false,
      "StageObjectCapture": null,
      "RaidID": 0,
      "FarmElementID": 0,
      "CocoonID": 0,
      "ActivityMapConditionIDList": null,
      "OverrideMapIconType": -1,
      "OverrideMapStateIcons": null,
      "OverridePropName": {
        "hash": 371857150
      },
      "Dialog": null,
      "InteractIconType": "ChatMissionIcon",
      "DialogueTriggerSkipFakeAvatar": true,
      "InteractTitle": {
        "hash": 371857150
      },
      "CustomParameter": null,
      "MapCustomParameter": null,
      "NearestTeleportMappingInfoID": 0,
      "OverrideBoardShowList": null,
      "IsClientOnly": false,
      "OverrideTriggerValidGuestConfig": false,
      "TriggerValidGuest": {
        "ConfigType": "ByEntityType",
        "Npc": false,
        "NpcMonster": false,
        "LocalPlayer": true,
        "Teammember": true,
        "FakePlayer": false,
        "TargetList": null,
        "EvaluatedInstances": null
      },
      "TagOperation": "Override",
      "CameraCollisionPoint": {
        "x": 0.0,
        "y": 0.0,
        "z": 0.0,
        "magnitude": 0.0,
        "sqrMagnitude": 0.0
      },
      "CameraCenterEntityList": [],
      "IsOverrideAudioSwitch": false,
      "AudioSwitchGroupName": null,
      "AudioSwitchName": null,
      "OverrideReplaceMaterialKey": null,
      "LookAtPlayer": false,
      "LookAtPlayerTriggerRadius": 2.0,
      "SpawnConfig": {
        "OverrideSpawn": false,
        "EntitySpawnConfig": {
          "NeedBlackIn": true,
          "BlackInDistance": 25.0,
          "NeedFadeIn": true,
          "NeedFadeOut": true
        }
      }
    },
    {
      "ID": 300013,
      "PosX": 402.8900146484375,
      "PosY": -15.979999542236328,
      "PosZ": 814.82000732421875,
      "IsDelete": false,
      "Name": "Cam02_Anchor1_Iso_Eff_special",
      "RotY": 0.0,
      "RotX": 0.0,
      "RotZ": 0.0,
      "Scale": {
        "x": 1.0,
        "y": 1.0,
        "z": 1.0,
        "normalized": {
          "x": 0.577350259,
          "y": 0.577350259,
          "z": 0.577350259,
          "normalized": {
            "x": 0.5773503,
            "y": 0.5773503,
            "z": 0.5773503,
            "magnitude": 1.00000012,
            "sqrMagnitude": 1.00000024
          },
          "magnitude": 0.99999994,
          "sqrMagnitude": 0.99999994
        },
        "magnitude": 1.73205078,
        "sqrMagnitude": 3.0
      },
      "PropID": 103085,
      "LoadOnInitial": true,
      "IsOverrideInitLevelGraph": false,
      "InitLevelGraph": null,
      "ValueSource": {
        "Values": [
          {
            "Value": "EffectEmit_OnAnchor1_Special_Case2",
            "Key": "GroupEventStringForEmit"
          }
        ],
        "SharedValues": [
          {
            "Value": "EffectEmit_OnAnchor1_Special_Case2",
            "Key": "GroupEventStringForEmit"
          }
        ]
      },
      "Trigger": null,
      "CampID": 4,
      "State": "Closed",
      "EventID": 0,
      "OverrideHintRange": -1.0,
      "OverrideSoundRange": -1.0,
      "CustomTriggerMap": {},
      "CustomTriggerMapV2": {},
      "BridgeStateRotations": [],
      "AnchorGroupID": 0,
      "AnchorID": 0,
      "ChestID": 0,
      "MappingInfoID": 0,
      "SubMapID": 0,
      "DialogueTriggerAngle": 120,
      "DialogueGroups": [],
      "FirstDialogueGroupID": 0,
      "TalkDialogGroupIDList": [],
      "TalkChosenType": "undefined",
      "ServerInteractVerificationIDList": [],
      "HideInCutScene": false,
      "HideInStory": false,
      "PerformanceHideFlags": 0,
      "DisableDither": false,
      "StageObjectCapture": null,
      "RaidID": 0,
      "FarmElementID": 0,
      "CocoonID": 0,
      "ActivityMapConditionIDList": null,
      "OverrideMapIconType": -1,
      "OverrideMapStateIcons": null,
      "OverridePropName": {
        "hash": 371857150
      },
      "Dialog": null,
      "InteractIconType": "ChatMissionIcon",
      "DialogueTriggerSkipFakeAvatar": true,
      "InteractTitle": {
        "hash": 371857150
      },
      "CustomParameter": null,
      "MapCustomParameter": null,
      "NearestTeleportMappingInfoID": 0,
      "OverrideBoardShowList": null,
      "IsClientOnly": false,
      "OverrideTriggerValidGuestConfig": false,
      "TriggerValidGuest": {
        "ConfigType": "ByEntityType",
        "Npc": false,
        "NpcMonster": false,
        "LocalPlayer": true,
        "Teammember": true,
        "FakePlayer": false,
        "TargetList": null,
        "EvaluatedInstances": null
      },
      "TagOperation": "Override",
      "CameraCollisionPoint": {
        "x": 0.0,
        "y": 0.0,
        "z": 0.0,
        "magnitude": 0.0,
        "sqrMagnitude": 0.0
      },
      "CameraCenterEntityList": [],
      "IsOverrideAudioSwitch": false,
      "AudioSwitchGroupName": null,
      "AudioSwitchName": null,
      "OverrideReplaceMaterialKey": null,
      "LookAtPlayer": false,
      "LookAtPlayerTriggerRadius": 2.0,
      "SpawnConfig": {
        "OverrideSpawn": false,
        "EntitySpawnConfig": {
          "NeedBlackIn": true,
          "BlackInDistance": 25.0,
          "NeedFadeIn": true,
          "NeedFadeOut": true
        }
      }
    }
  ],
  "DistrictList": [],
  "WaypointList": [],
  "PathwayList": [],
  "BattleAreaList": [],
  "NPCList": [],
  "CrowdList": [],
  "PedestrianList": [],
  "SmartObjectList": []
}